q3.v
module q1(a,b,c,d,f,g);
    input a,b,c,d;
    output f,g;
    assign f = ((~a)&d)|((~c)&d);
    assign g = ~((~((~((~(d|d))|a)) | (~((~(d|d))|c)))) | (~((~((~(d|d))|a)) | (~((~(d|d))|c))))) ;
endmodule

q3_tb.v
`timescale 1ns/1ns
`include "q3.v" //Name of the Verilog file
module q3_tb();
reg a,b,c,d;
//Input
wire f,g;
//Output
q1 qx1(a,b,c,d,f,g); //Instantiation of the module
initial
begin
$dumpfile("q3_tb.vcd");
$dumpvars(0, q3_tb);
a=1'b0;b=1'b0; c=1'b0; d=1'b0;
#20;
a=1'b0;b=1'b0; c=1'b0; d=1'b1;
#20;
a=1'b0;b=1'b0; c=1'b1; d=1'b0;
#20;
a=1'b0;b=1'b0; c=1'b1; d=1'b1;
#20;
a=1'b0;b=1'b1; c=1'b0; d=1'b0;
#20;
a=1'b0;b=1'b1; c=1'b0; d=1'b1;
#20;
a=1'b0;b=1'b1; c=1'b1; d=1'b0;
#20;
a=1'b0;b=1'b1; c=1'b1; d=1'b1;
#20;
a=1'b1;b=1'b0; c=1'b0; d=1'b0;
#20;
a=1'b1;b=1'b0; c=1'b0; d=1'b1;
#20;
a=1'b1;b=1'b0; c=1'b1; d=1'b0;
#20;
a=1'b1;b=1'b0; c=1'b1; d=1'b1;
#20;
a=1'b1;b=1'b1; c=1'b0; d=1'b0;
#20;
a=1'b1;b=1'b1; c=1'b0; d=1'b1;
#20;
a=1'b1;b=1'b1; c=1'b1; d=1'b0;
#20;
a=1'b1;b=1'b1; c=1'b1; d=1'b1;
#20;
$display("Test complete");
end
endmodule

q3_tb.vcd
$date
	Tue Sep 13 09:38:08 2022
$end
$version
	Icarus Verilog
$end
$timescale
	1ns
$end
$scope module q3_tb $end
$var wire 1 ! g $end
$var wire 1 " f $end
$var reg 1 # a $end
$var reg 1 $ b $end
$var reg 1 % c $end
$var reg 1 & d $end
$scope module qx1 $end
$var wire 1 # a $end
$var wire 1 $ b $end
$var wire 1 % c $end
$var wire 1 & d $end
$var wire 1 " f $end
$var wire 1 ! g $end
$upscope $end
$upscope $end
$enddefinitions $end
#0
$dumpvars
0&
0%
0$
0#
0"
0!
$end
#20
1!
1"
1&
#40
0!
0"
0&
1%
#60
1!
1"
1&
#80
0!
0"
0&
0%
1$
#100
1!
1"
1&
#120
0!
0"
0&
1%
#140
1!
1"
1&
#160
0!
0"
0&
0%
0$
1#
#180
1!
1"
1&
#200
0!
0"
0&
1%
#220
1&
#240
0!
0&
0%
1$
#260
1!
1"
1&
#280
0!
0"
0&
1%
#300
1&
